{
  "name": "巨斧",
  "icon": "simplyswords:iron_greataxe",
  "category": "simplyswords:category_weapon_variants",
  "pages": [
    {
      "type": "patchouli:spotlight",
      "item": "simplyswords:iron_greataxe",
      "text": "巨斧需要高水平的技巧才能有效地使用。这是一种双手武器，使用者需要用双手握持并挥动武器。"
    },
    {
      "type": "patchouli:crafting",
      "recipe": "simplyswords:iron_greataxe",
      "recipe2": "simplyswords:gold_greataxe"
    },
    {
      "type": "patchouli:crafting",
      "recipe": "simplyswords:diamond_greataxe"
    },
    {
      "type": "patchouli:smithing",
      "recipe": "simplyswords:netherite_greataxe",
      "recipe2": "simplyswords:runic_greataxe"
    }
  ]
}